LICENSE
README.md
setup.py
tap_3plcentral/__init__.py
tap_3plcentral/client.py
tap_3plcentral/discover.py
tap_3plcentral/schema.py
tap_3plcentral/sync.py
tap_3plcentral/transform.py
tap_3plcentral.egg-info/PKG-INFO
tap_3plcentral.egg-info/SOURCES.txt
tap_3plcentral.egg-info/dependency_links.txt
tap_3plcentral.egg-info/entry_points.txt
tap_3plcentral.egg-info/requires.txt
tap_3plcentral.egg-info/top_level.txt
tap_3plcentral/schemas/customers.json
tap_3plcentral/schemas/inventory.json
tap_3plcentral/schemas/locations.json
tap_3plcentral/schemas/orders.json
tap_3plcentral/schemas/sku_items.json
tap_3plcentral/schemas/stock_details.json
tap_3plcentral/schemas/stock_summaries.json